fennel/.gitignore
fennel/CHANGELOG.md
fennel/__init__.py
fennel/_vendor/README.md
fennel/_vendor/astunparse/LICENSE
fennel/_vendor/astunparse/__init__.py
fennel/_vendor/astunparse/__main__.py
fennel/_vendor/astunparse/printer.py
fennel/_vendor/astunparse/unparser.py
fennel/_vendor/astunparse.pyi
fennel/_vendor/certifi/LICENSE
fennel/_vendor/certifi/__init__.py
fennel/_vendor/certifi/__main__.py
fennel/_vendor/certifi/cacert.pem
fennel/_vendor/certifi/core.py
fennel/_vendor/certifi/py.typed
fennel/_vendor/chardet/LICENSE
fennel/_vendor/chardet/__init__.py
fennel/_vendor/chardet/big5freq.py
fennel/_vendor/chardet/big5prober.py
fennel/_vendor/chardet/chardistribution.py
fennel/_vendor/chardet/charsetgroupprober.py
fennel/_vendor/chardet/charsetprober.py
fennel/_vendor/chardet/cli/__init__.py
fennel/_vendor/chardet/cli/chardetect.py
fennel/_vendor/chardet/codingstatemachine.py
fennel/_vendor/chardet/codingstatemachinedict.py
fennel/_vendor/chardet/cp949prober.py
fennel/_vendor/chardet/enums.py
fennel/_vendor/chardet/escprober.py
fennel/_vendor/chardet/escsm.py
fennel/_vendor/chardet/eucjpprober.py
fennel/_vendor/chardet/euckrfreq.py
fennel/_vendor/chardet/euckrprober.py
fennel/_vendor/chardet/euctwfreq.py
fennel/_vendor/chardet/euctwprober.py
fennel/_vendor/chardet/gb2312freq.py
fennel/_vendor/chardet/gb2312prober.py
fennel/_vendor/chardet/hebrewprober.py
fennel/_vendor/chardet/jisfreq.py
fennel/_vendor/chardet/johabfreq.py
fennel/_vendor/chardet/johabprober.py
fennel/_vendor/chardet/jpcntx.py
fennel/_vendor/chardet/langbulgarianmodel.py
fennel/_vendor/chardet/langgreekmodel.py
fennel/_vendor/chardet/langhebrewmodel.py
fennel/_vendor/chardet/langhungarianmodel.py
fennel/_vendor/chardet/langrussianmodel.py
fennel/_vendor/chardet/langthaimodel.py
fennel/_vendor/chardet/langturkishmodel.py
fennel/_vendor/chardet/latin1prober.py
fennel/_vendor/chardet/macromanprober.py
fennel/_vendor/chardet/mbcharsetprober.py
fennel/_vendor/chardet/mbcsgroupprober.py
fennel_ai-1.5.80.dist-info/METADATA
fennel_ai-1.5.80.dist-info/WHEEL
fennel_ai-1.5.80.dist-info/RECORD
