Metadata-Version: 2.3
Name: fennel-ai
Version: 1.5.80
Summary: The modern realtime feature engineering platform
Author: Fennel AI
Author-email: developers@fennel.ai
Requires-Python: >=3.9,<4.0
Classifier: Programming Language :: Python :: 3
Classifier: Programming Language :: Python :: 3.9
Classifier: Programming Language :: Python :: 3.10
Classifier: Programming Language :: Python :: 3.11
Classifier: Programming Language :: Python :: 3.12
Classifier: Programming Language :: Python :: 3.13
Requires-Dist: attrs (>=24.3.0,<25.0.0)
Requires-Dist: fennel-data-lib (==0.1.27)
Requires-Dist: frozendict (>=2.3.8,<3.0.0)
Requires-Dist: numpy (==1.24.4) ; python_version < "3.12"
Requires-Dist: numpy (>=1.26.3,<2.0.0) ; python_version == "3.12"
Requires-Dist: pandas[performance] (>=2.2.2,<3.0.0)
Requires-Dist: protobuf (>=4.22.4,<5.0.0)
Requires-Dist: pyarrow (>=16.0.0,<17.0.0)
Requires-Dist: pycurl (>=7.45.4,<8.0.0)
Requires-Dist: pytest (==7.1.3)
Requires-Dist: pytest-rerunfailures (>=13.0,<14.0)
Requires-Dist: pytest-timeout (>=2.2.0,<3.0.0)
Requires-Dist: sortedcontainers (>=2.4.0,<3.0.0)
Requires-Dist: twine (>=6.0.1,<7.0.0)
Requires-Dist: typing-extensions (>=4.12.0,<5.0.0)
